vetl/__init__.py
vetl/core/__init__.py
vetl/core/config.py
vetl/core/database.py
vetl/core/file.py
vetl/core/tunnel.py
vetl/core/aws/__init__.py
vetl/core/aws/s3.py
vetl/core/aws/secret.py
vetl/core/aws/sts.py
vetl/core/log/__init__.py
vetl/core/log/activity.py
vetl/core/log/error.py
vetl_binary-0.0.0b2.dist-info/METADATA
vetl_binary-0.0.0b2.dist-info/WHEEL
vetl_binary-0.0.0b2.dist-info/top_level.txt
vetl_binary-0.0.0b2.dist-info/RECORD
