Metadata-Version: 2.1
Name: vetl-binary
Version: 0.0.0b2
Summary: Virtual ETL Tools
Home-page: https://github.com/asyraf-adianto/vetl
Author: Asyraf N. Adianto
Author-email: asyraf.adianto@gmail.com
License: MIT
Platform: UNKNOWN
Requires-Python: >=3.0
